<?xml version="1.0" encoding="UTF-8"?>

<Practitioner xmlns="http://hl7.org/fhir">
  <id value="4e2ed22a-95c8-4403-87fa-9a6a171ddc8b"/>
  <meta>
    <profile value="http://ns.electronichealth.net.au/ci/fhir/3.0/StructureDefinition/practitioner-ident-1"/>
  </meta>
  <text>
    <status value="generated"/><div xmlns="http://www.w3.org/1999/xhtml"><p><b>Generated Narrative with Details</b></p><p><b>id</b>: 4e2ed22a-95c8-4403-87fa-9a6a171ddc8b</p><p><b>meta</b>: </p><p><b>identifier</b>: EI = north27</p><p><b>name</b>: North Black </p></div>
  </text>
  <identifier>
    <type>
      <coding>
        <system value="http://terminology.hl7.org/CodeSystem/v2-0203"/>
        <code value="EI"/>
      </coding>
    </type>
    <system value="http://ns.electronichealth.net.au/id/abn-scoped/service-provider-individual/1.0/51824994455"/>
    <value value="north27"/>
    <assigner>
      <display value="Ascot Vale Family Medical Centre"/>
    </assigner>
  </identifier>
  <name>
    <family value="Black"/>
    <given value="North"/>
    <suffix value="M.D."/>
  </name>
</Practitioner>