{
  "resourceType": "Encounter",
  "id": "6c39fd65-2a5f-42d0-b3db-20b6416e2b9a",
  "meta": {
    "lastUpdated": "2019-06-03T11:00:00+10:00"
  },
  "text": {
    "status": "generated",
    "div": "<div xmlns=\"http://www.w3.org/1999/xhtml\"><p><b>Generated Narrative with Details</b></p><p><b>id</b>: 6c39fd65-2a5f-42d0-b3db-20b6416e2b9a</p><p><b>meta</b>: </p><p><b>status</b>: finished</p><p><b>class</b>: outpatient (Details: [not stated] code outpatient = 'outpatient', stated as 'null')</p><p><b>subject</b>: <a href=\"Patient-3a72f2d2-c9ed-40a4-beac-01c14dcf244a.html\">Generated Summary: id: 3a72f2d2-c9ed-40a4-beac-01c14dcf244a; Health Card Number = 307111942H; Gough Goodpatient ; gender: male</a></p><p><b>period</b>: 30/05/2019 9:00:00 AM --&gt; 30/05/2019 9:30:00 AM</p></div>"
  },
  "extension": [
    {
      "url": "http://hl7.org.au/fhir/StructureDefinition/encounter-description",
      "valueString": "Patient presented for follow-up with urinary tract infection on 30 May. Complaining of frequent and painful urinating.     Midstream urine test was done and revealed urinary infection. Culture and sensitivity test discovered escherichia coli sensitive to Bactrim.    Patient was prescribed Bactrim 2 tablets twice a day, and Panadol one tablet 4 times a day. Patient has no allergies."
    }
  ],
  "status": "finished",
  "class": {
    "code": "outpatient"
  },
  "subject": {
    "reference": "Patient/3a72f2d2-c9ed-40a4-beac-01c14dcf244a"
  },
  "period": {
    "start": "2019-05-30T09:00:00+10:00",
    "end": "2019-05-30T09:30:00+10:00"
  }
}