{
  "resourceType": "MedicationStatement",
  "id": "177a2cf1-71c2-470f-a625-52fb64ff116b",
  "text": {
    "status": "generated",
    "div": "<div xmlns=\"http://www.w3.org/1999/xhtml\"><p><b>Generated Narrative with Details</b></p><p><b>id</b>: 177a2cf1-71c2-470f-a625-52fb64ff116b</p><p><b>status</b>: active</p><p><b>medication</b>: Mega B complex <span style=\"background: LightGoldenRodYellow\">(Details )</span></p><p><b>subject</b>: <a href=\"Patient-47aa2cc5-5f17-44b5-9360-9e9df03973a6.html\">Generated Summary: id: 47aa2cc5-5f17-44b5-9360-9e9df03973a6; National unique individual identifier = 8003608833357361; Verily GoodPatient ; gender: other</a></p><p><b>taken</b>: y</p><p><b>dosage</b>: </p></div>"
  },
  "status": "active",
  "medicationCodeableConcept": {
    "text": "Mega B complex"
  },
  "subject": {
    "reference": "Patient/47aa2cc5-5f17-44b5-9360-9e9df03973a6"
  },
  "taken": "y",
  "dosage": [
    {
      "text": "1 d"
    }
  ]
}